src/__init__.py
src/__main__.py
src/cli.py
src/server.py
src/client/__init__.py
src/client/action_runs.py
src/client/actions.py
src/client/agent.py
src/client/blueprints.py
src/client/client.py
src/client/entities.py
src/client/permissions.py
src/client/scorecards.py
src/config/__init__.py
src/config/server_config.py
src/handlers/__init__.py
src/handlers/call_tool.py
src/maps/__init__.py
src/maps/tool_map.py
src/models/__init__.py
src/models/action_run/__init__.py
src/models/action_run/action_run.py
src/models/actions/__init__.py
src/models/actions/action.py
src/models/agent/__init__.py
src/models/agent/port_agent_response.py
src/models/blueprints/__init__.py
src/models/blueprints/blueprint.py
src/models/common/__init__.py
src/models/common/annotations.py
src/models/common/base_pydantic.py
src/models/common/icon.py
src/models/entities/__init__.py
src/models/entities/entity.py
src/models/permissions/__init__.py
src/models/permissions/get_action_permissions.py
src/models/permissions/update_action_policies.py
src/models/resources/__init__.py
src/models/resources/resource.py
src/models/resources/resource_map.py
src/models/scorecards/__init__.py
src/models/scorecards/condition_property.py
src/models/scorecards/condition_property_tool.py
src/models/scorecards/schemas.py
src/models/scorecards/scorecard.py
src/models/tools/__init__.py
src/models/tools/tool.py
src/models/tools/tool_map.py
src/tools/__init__.py
src/tools/action/__init__.py
src/tools/action/create_action.py
src/tools/action/delete_action.py
src/tools/action/dynamic_actions.py
src/tools/action/get_action.py
src/tools/action/list_actions.py
src/tools/action/track_action_run.py
src/tools/action/update_action.py
src/tools/ai_agent/__init__.py
src/tools/ai_agent/invoke_ai_agent.py
src/tools/blueprint/__init__.py
src/tools/blueprint/create_blueprint.py
src/tools/blueprint/delete_blueprint.py
src/tools/blueprint/get_blueprint.py
src/tools/blueprint/get_blueprints.py
src/tools/blueprint/update_blueprint.py
mcp_server_port-0.2.21.dist-info/METADATA
mcp_server_port-0.2.21.dist-info/WHEEL
mcp_server_port-0.2.21.dist-info/entry_points.txt
mcp_server_port-0.2.21.dist-info/licenses/LICENSE
mcp_server_port-0.2.21.dist-info/RECORD
