Metadata-Version: 2.4
Name: mcp-server-port
Version: 0.2.21
Summary: A Model Context Protocol (MCP) server for Port.io
Author-email: Matan Grady <matan.grady@getport.io>
License-File: LICENSE
Requires-Python: >=3.13
Requires-Dist: httpx>=0.28.1
Requires-Dist: loguru>=0.7.2
Requires-Dist: mcp[cli]>=1.6.0
Requires-Dist: pydantic<3.0.0,>=2.11.3
Requires-Dist: pyport<=0.3.3,>=0.3.3
Requires-Dist: python-dotenv>=1.0.1
